LICENSES
README.md
setup.py
MOFUN_CCC/DLModel.py
MOFUN_CCC/Data_prep.py
MOFUN_CCC/Feature_selection.py
MOFUN_CCC/Main_predict.py
MOFUN_CCC/Main_train.py
MOFUN_CCC/Plots.py
MOFUN_CCC/__init__.py
MOFUN_CCC/utils.py
MOFUN_CCC.egg-info/PKG-INFO
MOFUN_CCC.egg-info/SOURCES.txt
MOFUN_CCC.egg-info/dependency_links.txt
MOFUN_CCC.egg-info/requires.txt
MOFUN_CCC.egg-info/top_level.txt